intake_dal/__init__.py
intake_dal/dal_catalog.py
intake_dal/dal_online.py
intake_dal/dal_source.py
intake_dal/in_memory_kv.py
intake_dal/testMe.py
intake_dal/tests/catalog.yaml
intake_dal/tests/conftest.py
intake_dal/tests/data/user_events.csv
intake_dal/tests/data/user_events.parquet
intake_dal/tests/test_dal_catalog.py
intake_dal/tests/test_dal_online.py
intake_dal/tests/test_dal_source.py
intake_dal-0.1.9.dist-info/entry_points.txt
intake_dal-0.1.9.dist-info/LICENSE
intake_dal-0.1.9.dist-info/WHEEL
intake_dal-0.1.9.dist-info/METADATA
intake_dal-0.1.9.dist-info/RECORD
