Metadata-Version: 2.1
Name: intake-dal
Version: 0.1.9
Summary: Intake single YAML hierarchical catalog.
Author: Zillow AI Platform
Requires-Python: >=3.6
Classifier: Development Status :: 2 - Pre-Alpha
Classifier: Intended Audience :: Developers
Classifier: License :: OSI Approved :: Apache Software License
Classifier: Natural Language :: English
Classifier: Programming Language :: Python :: 3
Classifier: Programming Language :: Python :: 3.6
Classifier: Programming Language :: Python :: 3.7
Classifier: Programming Language :: Python :: 3.8
Provides-Extra: doc
Requires-Dist: deepmerge (==0.1.0)
Requires-Dist: intake (==0.5.4)
Requires-Dist: intake-nested-yaml-catalog (==0.1.0)
Requires-Dist: pandavro (>=1.5.1,<2.0.0)
Requires-Dist: pyarrow (>=0.15.1)
Requires-Dist: pyyaml (==5.1.2)
Requires-Dist: toolz (>=0.10.0,<0.11.0)
Requires-Dist: vcver (>=0.2.10)
